fastapi_maintenance/__init__.py
fastapi_maintenance/_constants.py
fastapi_maintenance/_context.py
fastapi_maintenance/_core.py
fastapi_maintenance/_handlers.py
fastapi_maintenance/backends.py
fastapi_maintenance/cli.py
fastapi_maintenance/decorators.py
fastapi_maintenance/middleware.py
fastapi_maintenance/py.typed
fastapi_maintenance-0.0.5.dist-info/METADATA
fastapi_maintenance-0.0.5.dist-info/WHEEL
fastapi_maintenance-0.0.5.dist-info/entry_points.txt
fastapi_maintenance-0.0.5.dist-info/licenses/LICENSE
fastapi_maintenance-0.0.5.dist-info/RECORD
