Metadata-Version: 2.4
Name: fastapi-maintenance
Version: 0.0.5
Summary: Flexible maintenance mode middleware for FastAPI applications.
Project-URL: Homepage, https://github.com/msamsami/fastapi-maintenance
Project-URL: Documentation, https://msamsami.github.io/fastapi-maintenance
Project-URL: Repository, https://github.com/msamsami/fastapi-maintenance
Project-URL: Issues, https://github.com/msamsami/fastapi-maintenance/issues
Author-email: Mehdi Samsami <mehdisamsami@live.com>
License-File: LICENSE
Keywords: 503,fastapi,maintenance,offline,unavailable
Classifier: Framework :: FastAPI
Classifier: Intended Audience :: Developers
Classifier: License :: OSI Approved :: MIT License
Classifier: Operating System :: OS Independent
Classifier: Programming Language :: Python :: 3
Classifier: Programming Language :: Python :: 3.8
Classifier: Programming Language :: Python :: 3.9
Classifier: Programming Language :: Python :: 3.10
Classifier: Programming Language :: Python :: 3.11
Classifier: Programming Language :: Python :: 3.12
Classifier: Programming Language :: Python :: 3.13
Requires-Python: >=3.8
Requires-Dist: fastapi>=0.99.0
Requires-Dist: typing-extensions>=4.8.0; python_full_version < '3.10'
Provides-Extra: cli
Requires-Dist: rich>=14.0.0; extra == 'cli'
Requires-Dist: typer>=0.16.0; extra == 'cli'
